mcp_openai/__init__.py
mcp_openai/client.py
mcp_openai/config.py
mcp_openai/py.typed
mcp_openai-0.2.0.dist-info/METADATA
mcp_openai-0.2.0.dist-info/WHEEL
mcp_openai-0.2.0.dist-info/licenses/LICENSE
mcp_openai-0.2.0.dist-info/RECORD
