Metadata-Version: 2.4
Name: mcp-openai
Version: 0.2.0
Summary: MCP Client with OpenAI compatible API
Project-URL: Homepage, https://github.com/S1M0N38/mcp-openai
Project-URL: Issues, https://github.com/S1M0N38/mcp-openai/issues
Project-URL: Repository, https://github.com/S1M0N38/mcp-openai
Project-URL: Changelog, https://github.com/S1M0N38/mcp-openai/blob/main/CHANGELOG.md
Author-email: S1M0N38 <bertolottosimone@gmail.com>
License-File: LICENSE
Classifier: Development Status :: 1 - Planning
Classifier: Framework :: Pytest
Classifier: Intended Audience :: Developers
Classifier: License :: OSI Approved :: MIT License
Classifier: Programming Language :: Python :: 3.11
Classifier: Topic :: Scientific/Engineering :: Artificial Intelligence
Classifier: Topic :: Software Development :: Libraries :: Python Modules
Requires-Python: >=3.11
Requires-Dist: mcp>=1.1.2
Requires-Dist: openai>=1.58.1
Requires-Dist: python-dotenv>=1.0.1
